pysortlib/__init__.py
pysortlib/sorting.py
pysortlib/sorting_extra.py
pysortlib/utils.py
pysortlib-1.0.0.dist-info/LICENSE
pysortlib-1.0.0.dist-info/METADATA
pysortlib-1.0.0.dist-info/WHEEL
pysortlib-1.0.0.dist-info/RECORD
