Metadata-Version: 2.3
Name: pysortlib
Version: 1.0.0
Summary: Python Sorting Library
License: MIT
Keywords: sorting,algorithms,data structures
Author: Michal Šoltis
Author-email: msoltis@redhat.com
Requires-Python: >=3.13,<4.0
Classifier: License :: OSI Approved :: MIT License
Classifier: Operating System :: OS Independent
Classifier: Programming Language :: Python
Classifier: Programming Language :: Python :: 3
Classifier: Programming Language :: Python :: 3.13
Classifier: Topic :: Education
Classifier: Topic :: Software Development :: Libraries :: Python Modules
Project-URL: Repository, https://github.com/slimreaper35/pysortlib
